{
  "MqttBrokerUri": "10.1.1.86",
  "Logos": [
    {
      "IpAddress": "10.1.1.230",
      "MemoryRanges": [
        {
          "LocalVariableMemoryPollingCycleMilliseconds": 100,
          "LocalVariableMemoryStart": 0,
          "LocalVariableMemoryEnd": 150
        }
      ],
      "Mqtt": [
        {
          "ClientId": "logo",
          "LastWill": {
            "Topic": "logo/status",
            "Payload": "unexpected gone offline",
            "QualityOfService": "ExactlyOnce"
          },
          "Channels": [
            {
              "Action": "publish",
              "Topic": "logo/q1/get",
              "LogoAddress": 111,
              "Type": "byte"
            },
            {
              "Action": "subscribePulse",
              "Topic": "logo/q1/set",
              "LogoAddress": 11,
              "Type": "byte"
            },

            {
              "Action": "publish",
              "Topic": "logo/q2/get",
              "LogoAddress": 112,
              "Type": "byte"
            },
            {
              "Action": "subscribe",
              "Topic": "logo/q2/set",
              "LogoAddress": 12,
              "Type": "byte"
            },

            {
              "Action": "publish",
              "Topic": "logo/q3/get",
              "LogoAddress": 113,
              "Type": "byte",
              "QualityOfService": "ExactlyOnce"
            },
            {
              "Action": "subscribe",
              "Topic": "logo/q3/set",
              "LogoAddress": 13,
              "Type": "byte",
              "QualityOfService": "ExactlyOnce"
            },

            {
              "Action": "publish",
              "Topic": "logo/q4/get",
              "LogoAddress": 114,
              "Type": "byte",
              "QualityOfService": "AtLeastOnce"
            },
            {
              "Action": "subscribe",
              "Topic": "logo/q4/set",
              "LogoAddress": 14,
              "Type": "byte",
              "QualityOfService": "AtLeastOnce"
            },


            {
              "Topic": "logo/i1/get",
              "LogoAddress": 1,
              "Type": "byte"
            },
            {
              "Topic": "logo/i2/get",
              "LogoAddress": 2,
              "Type": "byte"
            },
            {
              "Topic": "logo/i3/get",
              "LogoAddress": 3,
              "Type": "byte"
            },
            {
              "Topic": "logo/i4/get",
              "LogoAddress": 4,
              "Type": "byte"
            },
            {
              "Topic": "logo/i5/get",
              "LogoAddress": 5,
              "Type": "byte"
            },
            {
              "Topic": "logo/i6/get",
              "LogoAddress": 6,
              "Type": "byte"
            },
            {
              "Topic": "logo/i7/get",
              "LogoAddress": 7,
              "Type": "byte"
            },
            {
              "Topic": "logo/i8/get",
              "LogoAddress": 8,
              "Type": "byte"
            },

            
            {
              "Topic": "logo/F1/get",
              "LogoAddress": 101,
              "Type": "byte"
            },
            {
              "Topic": "logo/F2/get",
              "LogoAddress": 102,
              "Type": "byte"
            },
            {
              "Topic": "logo/F3/get",
              "LogoAddress": 103,
              "Type": "byte"
            },
            {
              "Topic": "logo/F4/get",
              "LogoAddress": 104,
              "Type": "byte"
            }

          ]
        }
      ]
    }
  ]
}
